gfpro_irrigation_control/__init__.py
gfpro_irrigation_control/cli.py
gfpro_irrigation_control/mqtt.py
gfpro_irrigation_control/valve.py
gfpro_irrigation_control-0.1.dist-info/METADATA
gfpro_irrigation_control-0.1.dist-info/WHEEL
gfpro_irrigation_control-0.1.dist-info/entry_points.txt
gfpro_irrigation_control-0.1.dist-info/RECORD
