Metadata-Version: 2.1
Name: gfpro-irrigation-control
Version: 0.1
Summary: 
License: MIT
Author: Tomas Bayer
Author-email: mail@tomas.berlin
Requires-Python: >=3.7,<4.0
Classifier: License :: OSI Approved :: MIT License
Classifier: Programming Language :: Python :: 3
Classifier: Programming Language :: Python :: 3.7
Classifier: Programming Language :: Python :: 3.8
Classifier: Programming Language :: Python :: 3.9
Classifier: Programming Language :: Python :: 3.10
Classifier: Programming Language :: Python :: 3.11
Classifier: Programming Language :: Python :: 3.12
Requires-Dist: bluepy (>=1.3.0,<2.0.0)
Requires-Dist: paho-mqtt (>=1.5.0,<2.0.0)
